<?xml version="1.0" encoding="utf-8" ?>
<Defs>

  <PawnKindDef ParentName="AnimalKindBase">
    <defName>MachnorianChicken</defName>
    <label>machnorian chicken</label>
    <labelMale>machnorian rooster</labelMale>
    <labelFemale>machnorian hen</labelFemale>
    <race>MachnorianChicken</race>
    <combatPower>30</combatPower>
    <ecoSystemWeight>0.30</ecoSystemWeight>
    <lifeStages>
      <li>
        <label>machnorian chick</label>
        <bodyGraphicData>
          <texPath>Things/Pawn/Animal/Machnor/Chicken</texPath>
          <drawSize>0.45</drawSize>
          <color>(223,219,108)</color>
        </bodyGraphicData>
        <dessicatedBodyGraphicData>
          <texPath>Things/Pawn/Animal/Machnor/Dessicated_Chicken</texPath>
          <drawSize>0.45</drawSize>
        </dessicatedBodyGraphicData>
      </li>
      <li>
        <labelMale>machnorian cockerel</labelMale>
        <bodyGraphicData>
          <texPath>Things/Pawn/Animal/Machnor/Chicken</texPath>
          <drawSize>0.75</drawSize>
          <color>(200,150,85)</color>
        </bodyGraphicData>
        <femaleGraphicData>
          <texPath>Things/Pawn/Animal/Machnor/Chicken</texPath>
          <drawSize>0.73</drawSize>
        </femaleGraphicData>
        <dessicatedBodyGraphicData>
          <texPath>Things/Pawn/Animal/Machnor/Dessicated_Chicken</texPath>
          <drawSize>0.75</drawSize>
        </dessicatedBodyGraphicData>
        <femaleDessicatedBodyGraphicData>
          <texPath>Things/Pawn/Animal/Machnor/Dessicated_Chicken</texPath>
          <drawSize>0.73</drawSize>
        </femaleDessicatedBodyGraphicData>
      </li>
      <li>
        <bodyGraphicData>
          <texPath>Things/Pawn/Animal/Machnor/Chicken</texPath>
          <drawSize>0.87</drawSize>
          <color>(200,150,85)</color>
          <shadowData>
            <volume>(0.3, 0.4, 0.3)</volume>
            <offset>(0,0,-0.05)</offset>
          </shadowData>
        </bodyGraphicData>
        <femaleGraphicData>
          <texPath>Things/Pawn/Animal/Machnor/Chicken</texPath>
          <drawSize>0.85</drawSize>
        </femaleGraphicData>
        <dessicatedBodyGraphicData>
          <texPath>Things/Pawn/Animal/Machnor/Dessicated_Chicken</texPath>
          <drawSize>0.87</drawSize>
        </dessicatedBodyGraphicData>
        <femaleDessicatedBodyGraphicData>
          <texPath>Things/Pawn/Animal/Machnor/Dessicated_Chicken</texPath>
          <drawSize>0.85</drawSize>
        </femaleDessicatedBodyGraphicData>
      </li>
    </lifeStages>
  </PawnKindDef>

  <ThingDef ParentName="AnimalThingBase">
    <defName>MachnorianChicken</defName>
    <label>machnorian chicken</label>
    <description>An advanced farm bird, the machnorian chicken is raised for its hardy constitution and ability to bring joy. It has eggs that can be processed into yayo.</description>
    <statBases>
      <MoveSpeed>4.20</MoveSpeed>
      <MarketValue>100</MarketValue>
      <LeatherAmount>30</LeatherAmount>
      <ComfyTemperatureMin>-15</ComfyTemperatureMin>
	  <FilthRate>4</FilthRate>
    </statBases>
    <tools>
      <li>
        <label>claws</label>
        <capacities>
          <li>Scratch</li>
        </capacities>
        <power>10</power>
        <cooldownTime>1.5</cooldownTime>
        <linkedBodyPartsGroup>Feet</linkedBodyPartsGroup>
      </li>
      <li>
        <label>beak</label>
        <capacities>
          <li>Bite</li>
        </capacities>
        <power>15</power>
        <cooldownTime>2</cooldownTime>
        <linkedBodyPartsGroup>Beak</linkedBodyPartsGroup>
      </li>
      <li>
        <label>head</label>
        <capacities>
          <li>Blunt</li>
        </capacities>
        <power>5</power>
        <cooldownTime>1.5</cooldownTime>
        <linkedBodyPartsGroup>HeadAttackTool</linkedBodyPartsGroup>
        <ensureLinkedBodyPartsGroupAlwaysUsable>true</ensureLinkedBodyPartsGroupAlwaysUsable>
        <chanceFactor>0.2</chanceFactor>
      </li>
    </tools>
    <comps>
      <li Class="CompProperties_EggLayer">
        <eggUnfertilizedDef>EggMachnorChickenUnfertilized</eggUnfertilizedDef>
        <eggFertilizedDef>EggMachnorChickenFertilized</eggFertilizedDef>
        <eggFertilizationCountMax>1</eggFertilizationCountMax>
        <eggLayIntervalDays>1</eggLayIntervalDays>
        <eggCountRange>1</eggCountRange>
      </li>
    </comps>
    <race>
      <body>Bird</body>
      <baseHungerRate>0.14</baseHungerRate>
      <baseBodySize>0.80</baseBodySize>
      <baseHealthScale>1.15</baseHealthScale>
      <foodType>OmnivoreRoughAnimal</foodType>
      <trainability>Advanced</trainability>
      <wildness>0</wildness>
      <manhunterOnTameFailChance>0</manhunterOnTameFailChance>
      <manhunterOnDamageChance>0</manhunterOnDamageChance>
	  <roamMtbDays>7</roamMtbDays>
      <mateMtbHours>8</mateMtbHours>
      <lifeExpectancy>8</lifeExpectancy>
      <lifeStageAges>
        <li>
          <def>AnimalBabyTiny</def>
          <minAge>0</minAge>
          <soundWounded>Pawn_Chick_Call</soundWounded>
          <soundDeath>Pawn_Chick_Call</soundDeath>
          <soundCall>Pawn_Chick_Call</soundCall>
          <soundAngry>Pawn_Chick_Call</soundAngry>
        </li>
        <li>
          <def>AnimalJuvenile</def>
          <minAge>0.12</minAge>
        </li>
        <li>
          <def>AnimalAdult</def>
          <minAge>0.2</minAge>
          <soundWounded>Pawn_Chicken_Wounded</soundWounded>
          <soundDeath>Pawn_Chicken_Death</soundDeath>
          <soundCall>Pawn_Chicken_Call</soundCall>
          <soundAngry>Pawn_Chicken_Angry</soundAngry>
        </li>
      </lifeStageAges>
      <soundMeleeHitPawn>Pawn_Melee_SmallScratch_HitPawn</soundMeleeHitPawn>
      <soundMeleeHitBuilding>Pawn_Melee_SmallScratch_HitBuilding</soundMeleeHitBuilding>
      <soundMeleeMiss>Pawn_Melee_SmallScratch_Miss</soundMeleeMiss>
    </race>
    <tradeTags>
      <li>AnimalCommon</li>
      <li>AnimalFarm</li>
    </tradeTags>
  </ThingDef>

</Defs>